[
  {
    "place_id": "ChIJkwBJKrRPqEcRDPdcqstlh4w",
    "slug": "chelany-neukoelln"
  },
  {
    "place_id": "ChIJU_obRrZPqEcRwiFttUrvpmU",
    "slug": "cafe-brick-time"
  },
  {
    "place_id": "ChIJK6tjGbZPqEcR6tLh2swidpw",
    "slug": "la-femme-lahmacun-und-pide"
  },
  {
    "place_id": "ChIJRbcxEaBPqEcR5Jm7FZpGdGA",
    "slug": "gazzo-sourdough-pizza"
  },
  {
    "place_id": "ChIJA5RWz0VPqEcRhpB9_RgYync",
    "slug": "paran"
  },
  {
    "place_id": "ChIJFX8pNABPqEcRur6VU1uwUBo",
    "slug": "caputo-peppino"
  },
  {
    "place_id": "ChIJq7v8zvNPqEcR2SnQPrgdJBM",
    "slug": "kitten-deli"
  },
  {
    "place_id": "ChIJyS7uxctPqEcRFB5ezLucyFU",
    "slug": "kai-maison"
  },
  {
    "place_id": "ChIJGSs7sLVPqEcRVMBJlGXhCWY",
    "slug": "ammazza-che-pizza"
  },
  {
    "place_id": "ChIJBx2P_clPqEcRZmRjXf5js2A",
    "slug": "gel-goer"
  },
  {
    "place_id": "ChIJj4t4fbNPqEcRrIN39kzufhI",
    "slug": "ctr-chicken-kreuzberg"
  },
  {
    "place_id": "ChIJ63q2GbZPqEcRpeNPcdpQ7Tk",
    "slug": "berlin-kumru"
  },
  {
    "place_id": "ChIJwYBzfgBPqEcRBp7Tt4XAGwg",
    "slug": "malesori-restaurant-berlin"
  },
  {
    "place_id": "ChIJRYPFVgVPqEcRbaiY5z5nkAg",
    "slug": "madame-hobrecht-spti-hobrechtstrasse"
  },
  {
    "place_id": "ChIJs7-ioaBPqEcRWB7R-r32OW4",
    "slug": "nusrit-kebap-gemuese-doener-berlin"
  },
  {
    "place_id": "ChIJ1ZRX0elPqEcR_8_wrDzX_jY",
    "slug": "mangiare-neukoelln"
  },
  {
    "place_id": "ChIJs9rm1EdPqEcRDY3XhW5wQ3A",
    "slug": "la-maison-bleue"
  },
  {
    "place_id": "ChIJNx0NcbFPqEcRlFK-tvVwIEw",
    "slug": "chutnify-neuklln"
  },
  {
    "place_id": "ChIJr3Z6ZbNPqEcR-3vvqisF7IE",
    "slug": "senegambia-berlin"
  },
  {
    "place_id": "ChIJb4iEfS9PqEcRXqRUrL7rTkQ",
    "slug": "karam-orientalisch"
  },
  {
    "place_id": "ChIJyzi3TiBPqEcR0qVEISLPMr8",
    "slug": "noriboi-berlin"
  },
  {
    "place_id": "ChIJYWPS9qxPqEcR4VWyhAb-jpw",
    "slug": "burger-junkys"
  },
  {
    "place_id": "ChIJOdceeaxPqEcRMzQEnx_l6oM",
    "slug": "pizzeria-latino-bln"
  },
  {
    "place_id": "ChIJI2cPNgBPqEcRJ8tAV8cImBA",
    "slug": "curry-junctionxx"
  },
  {
    "place_id": "ChIJS2HCGKpPqEcRIVf3TrCPbOw",
    "slug": "hindi-restaurant"
  },
  {
    "place_id": "ChIJZbEGMwBPqEcR3GNDFagdXEI",
    "slug": "elsen-dner"
  },
  {
    "place_id": "ChIJZdratwBOqEcRTeLoQ1HPOn8",
    "slug": "brammibals-donuts-maybachufer"
  },
  {
    "place_id": "ChIJ8bfq57RPqEcREqXXVD43rh0",
    "slug": "villa-di-wow"
  },
  {
    "place_id": "ChIJF-fdO7VPqEcR9D7eSbi0uCg",
    "slug": "reichen-burger"
  },
  {
    "place_id": "ChIJIfJlYABPqEcRB5kiTPfzzZ8",
    "slug": "dirty-dumplings"
  },
  {
    "place_id": "ChIJX-fEkW9PqEcRTCT9RcMyrQk",
    "slug": "smooches-sandwich-laden"
  },
  {
    "place_id": "ChIJ9VpDjxJPqEcRMXdua8cUDt8",
    "slug": "berlin-ph"
  },
  {
    "place_id": "ChIJWXlm6f1PqEcRIs3P07oGCi8",
    "slug": "wunderlampe"
  },
  {
    "place_id": "ChIJCa695RhPqEcRz7miYlwqCmM",
    "slug": "lalibela-berlin"
  },
  {
    "place_id": "ChIJaTZfp6NPqEcRHFinzKFzr-Y",
    "slug": "fourty-years"
  },
  {
    "place_id": "ChIJ8T3lSKpPqEcR8mUyaUmy0ks",
    "slug": "baba-restaurant"
  },
  {
    "place_id": "ChIJfX618KFPqEcRWFbbnPnsboY",
    "slug": "mmaah-korean-bbq-express-kreuzberg"
  },
  {
    "place_id": "ChIJyQ9ZNEtOqEcRPQbOwPVFLEk",
    "slug": "nachtigall-libanesische-kche-berlin"
  },
  {
    "place_id": "ChIJpVvpUNxPqEcRU1Y96nAcls0",
    "slug": "the-visit-coffee-wiener-strasse"
  },
  {
    "place_id": "ChIJnUK5pFJOqEcRO0f1YyIyipA",
    "slug": "inderheld-shahjahan"
  },
  {
    "place_id": "ChIJA_dRJTJPqEcRBgs-CQPG2v8",
    "slug": "falafel-in-berlinde"
  },
  {
    "place_id": "ChIJj6VHnLdPqEcR07WF7n8ooTY",
    "slug": "tuk-tuk-masala-8db80d"
  },
  {
    "place_id": "ChIJjV5gYwBPqEcRXeEc4w3u4Sc",
    "slug": "ofra"
  },
  {
    "place_id": "ChIJteejyBBPqEcRZta933rFasU",
    "slug": "sool"
  },
  {
    "place_id": "ChIJeVq3CDVOqEcRba5RL1mUXDE",
    "slug": "akshar-indisches-restaurant"
  },
  {
    "place_id": "ChIJx3KaWUpOqEcRU2olxN66MRM",
    "slug": "baraka-berlin"
  },
  {
    "place_id": "ChIJ9zDfkUpOqEcRYzXkB9bvJMM",
    "slug": "khartoum-sudanesischer-imbiss"
  },
  {
    "place_id": "ChIJKQuSDJZPqEcRFuPD4ijBnJU",
    "slug": "kimchi-princess-berlin"
  },
  {
    "place_id": "ChIJf5LelkpOqEcR2j4ExpnFV6M",
    "slug": "mercan-restaurant"
  },
  {
    "place_id": "ChIJWTVNcTVOqEcRylY7btderHg",
    "slug": "adana-grillhaus"
  },
  {
    "place_id": "ChIJN462VOxPqEcRInaRJjOLBcM",
    "slug": "miranda-berlin"
  },
  {
    "place_id": "ChIJSzEqZzVOqEcRblWsfmHSb7U",
    "slug": "windburger-kreuzberg"
  },
  {
    "place_id": "ChIJA_cK9f5PqEcRam2Cg0F9GTQ",
    "slug": "home-of-dumplings"
  },
  {
    "place_id": "ChIJK06VPMVPqEcRXjxisw6XVsE",
    "slug": "soi189"
  },
  {
    "place_id": "ChIJ0c70wUpOqEcRUizUrY_mdm8",
    "slug": "chaparro"
  },
  {
    "place_id": "ChIJhZhMXcFPqEcRRdiKoVHAVLo",
    "slug": "bbq-chicken-berlin-kreuzberg"
  },
  {
    "place_id": "ChIJ948HSQBPqEcRYZOpqaINiRk",
    "slug": "romeos-sandwiches"
  },
  {
    "place_id": "ChIJJbq3VQZPqEcRfcyt3ymWO38",
    "slug": "caphe-hoa-2"
  },
  {
    "place_id": "ChIJH0adADVOqEcRg43L7nGiT1Y",
    "slug": "da-dante"
  },
  {
    "place_id": "ChIJJR4w8CtPqEcRjw-iv12RBUU",
    "slug": "maiyarap-berlin"
  },
  {
    "place_id": "ChIJ4wSH3qxRqEcRLyJVpH8CDPU",
    "slug": "sidhu-berlin"
  },
  {
    "place_id": "ChIJaZZ0139PqEcRdg8AcAgl2DE",
    "slug": "steel-bean"
  },
  {
    "place_id": "ChIJd-Iqs7JPqEcRgDX0A9_nnAU",
    "slug": "san-sebastian-kreuzberg-neu"
  },
  {
    "place_id": "ChIJuywQOkpOqEcRUJ2FMo5Ue20",
    "slug": "rocco-und-seine-brder"
  },
  {
    "place_id": "ChIJlV40EExOqEcRw-LRQsb4aos",
    "slug": "mcdonalds-wrangelstrasse"
  },
  {
    "place_id": "ChIJlQ0yd2JQqEcREMf7Y-d-Nco",
    "slug": "pan-africa-bln"
  },
  {
    "place_id": "ChIJbcqAmaIjZUERaMFeY4pV7VI",
    "slug": "chi-chu"
  },
  {
    "place_id": "ChIJ4W8MsEtOqEcR_TTjxwyJQjs",
    "slug": "hhnerhaus36"
  },
  {
    "place_id": "ChIJoaQbXwBPqEcRzefq86tUa3s",
    "slug": "wen-cheng-4-hand-pulled-noodles"
  },
  {
    "place_id": "ChIJWxowgylPqEcRd3oxONDXh1Q",
    "slug": "ngoc-chau-restaurant"
  },
  {
    "place_id": "ChIJk3b3IwNPqEcRaEM2c3uKmRs",
    "slug": "zerostress-pizza-kreuzberg"
  },
  {
    "place_id": "ChIJJXt0PABPqEcRQOdYkpvtiW0",
    "slug": "pirosmani-ber"
  },
  {
    "place_id": "ChIJa-T4zuNPqEcR-8trMvqPOvc",
    "slug": "sadhu-kreuzberg"
  },
  {
    "place_id": "ChIJ1ekxOAFPqEcRIAFyUzIGFJ4",
    "slug": "restaurant-dumplings-nian"
  },
  {
    "place_id": "ChIJtYhDQExOqEcRDwX2Fcy5raY",
    "slug": "ta-cabron-taqueria"
  },
  {
    "place_id": "ChIJfeorv01OqEcRIGW238pursw",
    "slug": "sumak-berlin"
  },
  {
    "place_id": "ChIJe_UjelJOqEcR37_wrA2r2Ro",
    "slug": "nour-wrangelstrasse"
  },
  {
    "place_id": "ChIJWU8hvk1OqEcR6GKwoqUvbRU",
    "slug": "pizzeria-toros"
  },
  {
    "place_id": "ChIJWdsAiFJOqEcR30pmtnlQEuc",
    "slug": "unka-koefteburger-berlin"
  },
  {
    "place_id": "ChIJ6-L121RPqEcRDiYlJ88ZErM",
    "slug": "kaiser-cafe-kreuzberg"
  },
  {
    "place_id": "ChIJVQ7GhCpPqEcRfDHzqLYtHSk",
    "slug": "slava-berlin"
  },
  {
    "place_id": "ChIJD4cEy01OqEcR43EXs3nDWOc",
    "slug": "tunas-gemuse-kebap"
  },
  {
    "place_id": "ChIJZ4ft7nNPqEcRMRgrBGaUrsk",
    "slug": "thung-thai-kreuzberg"
  },
  {
    "place_id": "ChIJfxxD5ZZPqEcRdJUVorywsQo",
    "slug": "imera-grill"
  },
  {
    "place_id": "ChIJ3Z5kYiRRqEcRxGcX91q-nxI",
    "slug": "mexicali-cantina-f10e74"
  },
  {
    "place_id": "ChIJQbhd9F1PqEcR0lizKRUEH84",
    "slug": "el-taco-loco"
  },
  {
    "place_id": "ChIJ5zcN6_hPqEcRUDLbX-xsb3o",
    "slug": "restaurant-yijia"
  },
  {
    "place_id": "ChIJ6fiyKitSqEcRVVsBRRLlVIQ",
    "slug": "parma-di-vinibenedetti"
  },
  {
    "place_id": "ChIJAetnwk1OqEcR4iHk5UeqDhg",
    "slug": "alisna-kumpir"
  },
  {
    "place_id": "ChIJRyyclqVPqEcRYJvgUHrMIpY",
    "slug": "gogihaus"
  },
  {
    "place_id": "ChIJfYNzNYxPqEcRCN_rJx6CR6w",
    "slug": "flat-berlin"
  },
  {
    "place_id": "ChIJqY2b9vpPqEcRiIUZyHazyeA",
    "slug": "the-hummusapiens"
  },
  {
    "place_id": "ChIJm94gD9hPqEcRPF07byVx9K8",
    "slug": "fam-tran"
  },
  {
    "place_id": "ChIJy0uke01OqEcRsWY7iaaw2Ik",
    "slug": "bantabaa-food-dealer"
  },
  {
    "place_id": "ChIJZ8lLffNPqEcRhCJk4uLlddc",
    "slug": "anitas-lunch"
  },
  {
    "place_id": "ChIJfziMc05OqEcR74o_HSkK5fg",
    "slug": "mikoto-sushi-kreuzberg"
  },
  {
    "place_id": "ChIJOfKD4k1OqEcRHmPoazDXK-w",
    "slug": "pizza-espresso"
  },
  {
    "place_id": "ChIJpyVAcGFPqEcR5b8kd72u4uI",
    "slug": "best-bistro-berlin"
  },
  {
    "place_id": "ChIJpbHIyk1OqEcR7Z1BcbA3wxk",
    "slug": "kali-caf-berlin"
  },
  {
    "place_id": "ChIJl_ArLadPqEcRG9MH5euaq5o",
    "slug": "kofain"
  },
  {
    "place_id": "ChIJ2Uh9Bk5OqEcREoy9N1LxImw",
    "slug": "burgermeister-schlesisches-tor-8"
  },
  {
    "place_id": "ChIJ8SCWPlJOqEcRJG5XrevdHsc",
    "slug": "restaurante-tapas-bar-faro"
  },
  {
    "place_id": "ChIJy-pIGFJOqEcRQbLaZ5vkUqs",
    "slug": "19grams-schlesi-berlin"
  },
  {
    "place_id": "ChIJydbDfU1OqEcRula0xZUaBXY",
    "slug": "burgersteig-berlin"
  },
  {
    "place_id": "ChIJKerUrfNPqEcR1ZuFTi3blcI",
    "slug": "burger-city-schlesische-strae"
  },
  {
    "place_id": "ChIJZxXRX_BPqEcRV_IBMav_lE4",
    "slug": "falafel-damascino"
  },
  {
    "place_id": "ChIJQRX6Zp1PqEcRjovLmd9g4uc",
    "slug": "takumi-asian-cuisine-sushi-berlin"
  },
  {
    "place_id": "ChIJ-_wCElJOqEcR5VOvmIV7Ncs",
    "slug": "shaan"
  },
  {
    "place_id": "ChIJmeqeYABPqEcRb1U1iZ3DWmo",
    "slug": "tex-mex-ico-berlin"
  },
  {
    "place_id": "ChIJI6pkjWRPqEcRCO24cmcTzFo",
    "slug": "amore-milano"
  },
  {
    "place_id": "ChIJ9SaoXu5PqEcRj4DxAV2xbAE",
    "slug": "ma-pasta38"
  },
  {
    "place_id": "ChIJkYcgNeFPqEcRnlCJqilgMQ8",
    "slug": "abis-manti-und-goezleme"
  },
  {
    "place_id": "ChIJcxGZ4I5PqEcRb-4YP450Qf4",
    "slug": "omdur-homemade-sudanese-streetfood"
  },
  {
    "place_id": "ChIJLXm-qZRPqEcRmNIhyj2VJMw",
    "slug": "xudu"
  },
  {
    "place_id": "ChIJMQGM1ZpPqEcRUl1Y3eDQitU",
    "slug": "sunshine-vegan"
  },
  {
    "place_id": "ChIJxVl_GVJOqEcRS71E0-L47uA",
    "slug": "delikato"
  },
  {
    "place_id": "ChIJAcHUht5PqEcR3nGTFJUjs_E",
    "slug": "koshary-cairo"
  },
  {
    "place_id": "ChIJ3SVpcOBPqEcRBmHklZITNkw",
    "slug": "chung-asia-street-kitchen-schlesische-strasse"
  },
  {
    "place_id": "ChIJY8CwLb1PqEcRsrmrfjLgD-k",
    "slug": "il-pizzaiolo"
  },
  {
    "place_id": "ChIJafBhcoVPqEcRb7rHEy3G0L8",
    "slug": "maison-umami"
  },
  {
    "place_id": "ChIJC1ZpSQBPqEcRoQuu5qHYtDc",
    "slug": "best-chicken-berlin"
  },
  {
    "place_id": "ChIJVUD_u1NOqEcRNCh5VOOY2qk",
    "slug": "cafe-frida-berlin"
  },
  {
    "place_id": "ChIJBcVO6zpPqEcRF7EwDk3YOdg",
    "slug": "perbacco-ristorante-pizzeria"
  },
  {
    "place_id": "ChIJjfaBXlpPqEcRHmbrOSQgab4",
    "slug": "ginos-pizza-pasta-manteuffelstrasse"
  },
  {
    "place_id": "ChIJtYlLhklOqEcR--8WWqY2eVk",
    "slug": "mani-in-pasta"
  },
  {
    "place_id": "ChIJOSCN6DhPqEcRbcKZWrc-VzI",
    "slug": "ballers-place"
  },
  {
    "place_id": "ChIJU0lQH1lPqEcRgXYdcxfo4bc",
    "slug": "martins-crperie"
  },
  {
    "place_id": "ChIJDW04rk9OqEcRrw3jo_h8Ydw",
    "slug": "five-guys-friedrichshain"
  },
  {
    "place_id": "ChIJO6wvxE5OqEcR9ELBIBCiGbw",
    "slug": "salumeria-lamuri"
  },
  {
    "place_id": "ChIJT2EhTJ5PqEcR4KY1dPSYDBY",
    "slug": "mllers-kttbullar"
  },
  {
    "place_id": "ChIJQRz916NPqEcRL7G6mBICe5k",
    "slug": "zola-pizza-friedrichshain"
  },
  {
    "place_id": "ChIJ_-u_slFOqEcRc0jMpzKA48c",
    "slug": "scheers-schnitzel"
  },
  {
    "place_id": "ChIJT7tMTlBOqEcRBEi-SI8Dg70",
    "slug": "urban-falafel"
  },
  {
    "place_id": "ChIJtRN6FP5PqEcRGKUnBjJxtuw",
    "slug": "nepal-momo"
  },
  {
    "place_id": "ChIJNfp_dDNPqEcRGI1rr7IfOec",
    "slug": "curry-36"
  },
  {
    "place_id": "ChIJn0x_UgZPqEcRTbCcV7aaMbI",
    "slug": "poke-mana"
  },
  {
    "place_id": "ChIJM4vn7A1PqEcRaSsE2fwqnqk",
    "slug": "swadesh-south-and-north-indian-food"
  },
  {
    "place_id": "ChIJ53B9GldOqEcRNKk5ZEMrKvo",
    "slug": "la-cesta"
  }
]